{
    "gatto": [
        {
            "PrimaryKey": "it-gatto§Noun_ZOOLOGIA_MAMMALOGIA_SILVESTRIS_Piccolo-0-420",
            "SelfUrl": "https://it.wiktionary.org/wiki/gatto",
            "LabelName": "gatto",
            "LabelType": "Noun_ZOOLOGIA_MAMMALOGIA_SILVESTRIS_Piccolo",
            "LanguageCode": "it",
            "Type": "noun",
            "TypeLabelName": "",
            "ExplainationRaw": "# {{Term|zoologia|it}} {{Term|mammalogia|it}} [[piccolo]] [[mammifero]] [[domestico]] dell'ordine dei [[Carnivori]], [[della]] [[famiglia]] [[dei]] [[Felidi]], [[dal]] [[corpo]] [[agile]], con [[capo]] [[tondeggiante]], [[unghie]] [[retrattili]] e [[pelame]] di [[vario]] colore; {{Taxon|Felis silvestris catus}}",
            "ExplainationTxt": "piccolo mammifero domestico dell'ordine dei Carnivori, della famiglia dei Felidi, dal corpo agile, con capo tondeggiante, unghie retrattili e pelame di vario colore;",
            "ExplainationExamplesRaw": null,
            "ExplainationExamplesTxt": null,
            "IsMale": true,
            "IsFeminine": null,
            "IsNeutre": null,
            "IsSingle": true,
            "IsPlural": null,
            "SingleVariant": "gatto",
            "PluralVariant": "gatti",
            "PopularityOfWord": 0,
            "MaleVariant": "gatto",
            "FemaleVariant": "gatta",
            "IsVerbPast": null,
            "IsVerbPresent": null,
            "IsVerbFutur": null,
            "Conjugation": [],
            "Synonymy": [],
            "Antonymy": [],
            "Hypernymy": [],
            "Hyponymy": [],
            "Meronymy": [],
            "Holonymy": [],
            "Troponymy": [],
            "Otherwise": [],
            "AlternativeFormsOther": [],
            "RelatedTerms": [],
            "Coordinate": [],
            "Translation_EN": [],
            "Translation_FR": [],
            "Translation_DE": [],
            "Translation_IT": [],
            "Translation_ES": [],
            "Translation_RU": [],
            "Translation_PT": []
        },
        {
            "PrimaryKey": "it-gatto§Noun_FIG_Persona_Agilissima-1-333",
            "SelfUrl": "https://it.wiktionary.org/wiki/gatto",
            "LabelName": "gatto",
            "LabelType": "Noun_FIG_Persona_Agilissima",
            "LanguageCode": "it",
            "Type": "noun",
            "TypeLabelName": "",
            "ExplainationRaw": "# {{Fig}} [[persona]] [[agilissimo|agilissima]]",
            "ExplainationTxt": "persona agilissima",
            "ExplainationExamplesRaw": "#* ''quell'atleta è un {{Pn}}''",
            "ExplainationExamplesTxt": "''quell'atleta è un pn''",
            "IsMale": true,
            "IsFeminine": null,
            "IsNeutre": null,
            "IsSingle": true,
            "IsPlural": null,
            "SingleVariant": "gatto",
            "PluralVariant": "gatti",
            "PopularityOfWord": 155,
            "MaleVariant": "gatto",
            "FemaleVariant": "gatta",
            "IsVerbPast": null,
            "IsVerbPresent": null,
            "IsVerbFutur": null,
            "Conjugation": [],
            "Synonymy": [],
            "Antonymy": [],
            "Hypernymy": [],
            "Hyponymy": [],
            "Meronymy": [],
            "Holonymy": [],
            "Troponymy": [],
            "Otherwise": [],
            "AlternativeFormsOther": [],
            "RelatedTerms": [],
            "Coordinate": [],
            "Translation_EN": [],
            "Translation_FR": [],
            "Translation_DE": [],
            "Translation_IT": [],
            "Translation_ES": [],
            "Translation_RU": [],
            "Translation_PT": []
        },
        {
            "PrimaryKey": "it-gatto§Noun_FIG_Persona_Molto_Dolce-2-448",
            "SelfUrl": "https://it.wiktionary.org/wiki/gatto",
            "LabelName": "gatto",
            "LabelType": "Noun_FIG_Persona_Molto_Dolce",
            "LanguageCode": "it",
            "Type": "noun",
            "TypeLabelName": "",
            "ExplainationRaw": "# {{Fig}} [[persona]] [[molto]] [[dolce]]",
            "ExplainationTxt": "persona molto dolce",
            "ExplainationExamplesRaw": null,
            "ExplainationExamplesTxt": null,
            "IsMale": true,
            "IsFeminine": null,
            "IsNeutre": null,
            "IsSingle": true,
            "IsPlural": null,
            "SingleVariant": "gatto",
            "PluralVariant": "gatti",
            "PopularityOfWord": 0,
            "MaleVariant": "gatto",
            "FemaleVariant": "gatta",
            "IsVerbPast": null,
            "IsVerbPresent": null,
            "IsVerbFutur": null,
            "Conjugation": [],
            "Synonymy": [],
            "Antonymy": [],
            "Hypernymy": [],
            "Hyponymy": [],
            "Meronymy": [],
            "Holonymy": [],
            "Troponymy": [],
            "Otherwise": [],
            "AlternativeFormsOther": [],
            "RelatedTerms": [],
            "Coordinate": [],
            "Translation_EN": [],
            "Translation_FR": [],
            "Translation_DE": [],
            "Translation_IT": [],
            "Translation_ES": [],
            "Translation_RU": [],
            "Translation_PT": []
        },
        {
            "PrimaryKey": "it-gatto§Noun_ARALDICA_Araldica_Convenzionale_Animale-3-433",
            "SelfUrl": "https://it.wiktionary.org/wiki/gatto",
            "LabelName": "gatto",
            "LabelType": "Noun_ARALDICA_Araldica_Convenzionale_Animale",
            "LanguageCode": "it",
            "Type": "noun",
            "TypeLabelName": "",
            "ExplainationRaw": "# {{Term|araldica|it}} figura [[araldica]] [[convenzionale]] che rappresenta di norma l'[[animale]] [[passante]] e con la testa di fronte, nella [[posizione]] simile a quella del [[leopardo]]",
            "ExplainationTxt": "figura araldica convenzionale che rappresenta di norma l'animale passante e con la testa di fronte, nella posizione simile a quella del leopardo",
            "ExplainationExamplesRaw": null,
            "ExplainationExamplesTxt": null,
            "IsMale": true,
            "IsFeminine": null,
            "IsNeutre": null,
            "IsSingle": true,
            "IsPlural": null,
            "SingleVariant": "gatto",
            "PluralVariant": "gatti",
            "PopularityOfWord": 0,
            "MaleVariant": "gatto",
            "FemaleVariant": "gatta",
            "IsVerbPast": null,
            "IsVerbPresent": null,
            "IsVerbFutur": null,
            "Conjugation": [],
            "Synonymy": [],
            "Antonymy": [],
            "Hypernymy": [],
            "Hyponymy": [],
            "Meronymy": [],
            "Holonymy": [],
            "Troponymy": [],
            "Otherwise": [],
            "AlternativeFormsOther": [],
            "RelatedTerms": [],
            "Coordinate": [],
            "Translation_EN": [],
            "Translation_FR": [],
            "Translation_DE": [],
            "Translation_IT": [],
            "Translation_ES": [],
            "Translation_RU": [],
            "Translation_PT": []
        },
        {
            "PrimaryKey": "it-gatto§Noun_SPREG_Astuta_persona-4-393",
            "SelfUrl": "https://it.wiktionary.org/wiki/gatto",
            "LabelName": "gatto",
            "LabelType": "Noun_SPREG_Astuta_persona",
            "LanguageCode": "it",
            "Type": "noun",
            "TypeLabelName": "",
            "ExplainationRaw": "# {{Spreg}} persona [[astuta]]",
            "ExplainationTxt": "persona astuta",
            "ExplainationExamplesRaw": "#* ''si muove come un {{Pn}}''",
            "ExplainationExamplesTxt": "''si muove come un pn''",
            "IsMale": true,
            "IsFeminine": null,
            "IsNeutre": null,
            "IsSingle": true,
            "IsPlural": null,
            "SingleVariant": "gatto",
            "PluralVariant": "gatti",
            "PopularityOfWord": 150,
            "MaleVariant": "gatto",
            "FemaleVariant": "gatta",
            "IsVerbPast": null,
            "IsVerbPresent": null,
            "IsVerbFutur": null,
            "Conjugation": [],
            "Synonymy": [],
            "Antonymy": [],
            "Hypernymy": [],
            "Hyponymy": [],
            "Meronymy": [],
            "Holonymy": [],
            "Troponymy": [],
            "Otherwise": [],
            "AlternativeFormsOther": [],
            "RelatedTerms": [],
            "Coordinate": [],
            "Translation_EN": [],
            "Translation_FR": [],
            "Translation_DE": [],
            "Translation_IT": [],
            "Translation_ES": [],
            "Translation_RU": [],
            "Translation_PT": []
        }
    ]
}